[
	{
		"href": "/join/search",
		"id": 232,
		"name": "加盟商管理",
		"parentId": "",
		"projectPath": "",
		"seq": 18,
		"type": "0",
		"url": ""
	}, {
		"href": "",
		"id": 230,
		"name": "问题案件管理",
		"parentId": "",
		"projectPath": "",
		"seq": 16,
		"type": "0",
		"url": ""
	}, {
		"href": "/board/all",
		"id": 212,
		"name": "案件管理",
		"parentId": "",
		"projectPath": "",
		"seq": 15,
		"type": "0",
		"url": ""
	}, {
		"href": "",
		"id": 211,
		"name": "案件审批",
		"parentId": "",
		"projectPath": "",
		"seq": 17,
		"type": "0",
		"url": ""
	}, {
		"href": "",
		"id": 210,
		"name": "案件转移",
		"parentId": "",
		"projectPath": "",
		"seq": 16,
		"type": "0",
		"url": ""
	}, {
		"href": "/loan/sort",
		"id": 183,
		"name": "贷后管理",
		"parentId": "",
		"projectPath": "",
		"seq": 14,
		"type": "0",
		"url": ""
	}, {
		"href": "/sms/config",
		"id": 172,
		"name": "短信管理",
		"parentId": "",
		"projectPath": "",
		"seq": 13,
		"type": "0",
		"url": ""
	}, {
		"id": 1,
		"name": "任务管理",
		"seq": 0,
		"type": "0"
	}, {
		"id": 4,
		"name": "用户管理",
		"seq": 2,
		"type": "0"
	}, {
		"id": 6,
		"name": "订单管理",
		"seq": 1,
		"type": "0"
	}, {
		"href": "/work/process",
		"id": 10,
		"name": "工作流设置",
		"seq": 10,
		"type": "0"
	}, {
		"href": "/group/company",
		"id": 14,
		"name": "组织架构",
		"seq": 11,
		"type": "0"
	}, {
		"href": "/product/config",
		"id": 18,
		"name": "产品管理",
		"seq": 12,
		"type": "0"
	}
]